{
  "menu": [
    {
      "label": "Packages",
      "submenu": [
        {
          "label": "FTP editor",
          "submenu": [
            {
              "label": "Create and Initialize Settings",
              "command": "ftp-editor:create"
            },
            {
              "label": "Download Project",
              "command": "ftp-editor:download"
            }

          ]
        }
      ]
    }
  ],
  "context-menu": {
    ".tree-view": [],
    "atom-workspace": [
      {
        "label": "Download FTP",
        "command": "ftp-editor:current-download"
      },
      {
        "label": "upload FTP",
        "command": "ftp-editor:current-upload"
      }

    ]
  }
}
